{
  "parent": "minecraft:recipes/root",
  "rewards": {
    "recipes": [
      "doiamornament:arctic_fur_saddle_door"
    ]
  },
  "criteria": {
    "has_arctic_fur": {
      "trigger": "minecraft:inventory_changed",
      "conditions": {
        "items": [
          {
            "items": [
              "doiamornament:arctic_fur_trapdoor"
            ]
          }
        ]
      }
    },
    "has_the_recipe": {
      "trigger": "minecraft:recipe_unlocked",
      "conditions": {
        "recipe": "doiamornament:arctic_fur_saddle_door"
      }
    }
  },
  "requirements": [
    [
      "has_arctic_fur",
      "has_the_recipe"
    ]
  ]
}